tests/__init__.py
tests/conftest.py
tests/test_redis.py
tests/test_report_builder.py
tests/test_report_reader.py
tests/test_topology.py
tests/test_wotpy.py
wotemu/__init__.py
wotemu/__version__.py
wotemu/config.py
wotemu/enums.py
wotemu/utils.py
wotemu/apps/__init__.py
wotemu/apps/caller.py
wotemu/apps/camera.py
wotemu/apps/clock.py
wotemu/apps/detector.py
wotemu/apps/error.py
wotemu/apps/historian.py
wotemu/apps/reader.py
wotemu/apps/subscriber.py
wotemu/apps/worker.py
wotemu/apps/data/README.md
wotemu/apps/data/__init__.py
wotemu/apps/data/camera.mp4
wotemu/cli/__init__.py
wotemu/cli/app.py
wotemu/cli/broker.py
wotemu/cli/chaos.py
wotemu/cli/compose.py
wotemu/cli/limits.py
wotemu/cli/main.py
wotemu/cli/report.py
wotemu/cli/routes.py
wotemu/cli/stop.py
wotemu/cli/utils.py
wotemu/cli/waiter.py
wotemu/monitor/__init__.py
wotemu/monitor/base.py
wotemu/monitor/packet.py
wotemu/monitor/system.py
wotemu/monitor/utils.py
wotemu/report/__init__.py
wotemu/report/builder.py
wotemu/report/reader.py
wotemu/report/utils.py
wotemu/report/components/__init__.py
wotemu/report/components/base.py
wotemu/report/components/code_block.py
wotemu/report/components/container.py
wotemu/report/components/figure_block.py
wotemu/report/components/figures_row.py
wotemu/report/components/task_list.py
wotemu/report/components/task_section.py
wotemu/report/templates/base.html
wotemu/topology/__init__.py
wotemu/topology/compose.py
wotemu/topology/cpu.py
wotemu/topology/models.py
wotemu/wotpy/__init__.py
wotemu/wotpy/redis.py
wotemu/wotpy/things.py
wotemu/wotpy/wot.py
wotemu-0.6.0.dist-info/LICENSE
wotemu-0.6.0.dist-info/METADATA
wotemu-0.6.0.dist-info/WHEEL
wotemu-0.6.0.dist-info/entry_points.txt
wotemu-0.6.0.dist-info/top_level.txt
wotemu-0.6.0.dist-info/RECORD
