Metadata-Version: 2.1
Name: wotemu
Version: 0.6.0
Summary: An emulator for Python applications to help in the design of IoT deployments based on the edge computing model
Home-page: UNKNOWN
Author: Andres Garcia Mangas
Author-email: andres.garcia@fundacionctic.org
License: UNKNOWN
Keywords: wot iot edge emulator
Platform: UNKNOWN
Classifier: Programming Language :: Python :: 3.6
Classifier: Programming Language :: Python :: 3.7
Classifier: Programming Language :: Python :: 3.8
Classifier: Programming Language :: Python :: 3.9
Classifier: License :: OSI Approved :: MIT License
Classifier: Development Status :: 4 - Beta
Classifier: Operating System :: POSIX :: Linux
Requires-Python: >=3.6
License-File: LICENSE
Requires-Dist: docker (<5.0,>=4.1.0)
Requires-Dist: coloredlogs (<15.0,>=14.0)
Requires-Dist: netaddr (<0.8.0,>=0.7.19)
Requires-Dist: netifaces (<0.11.0,>=0.10.9)
Requires-Dist: Click (<8.0,>=7.0)
Requires-Dist: sh (<2.0,>=1.12.14)
Requires-Dist: wotpy (==0.14.5)
Requires-Dist: aioredis (<2.0,>=1.3)
Requires-Dist: tornado (<6.0,>=5.1)
Requires-Dist: PyYAML (<6.0,>=5.3)
Requires-Dist: inflection (<0.5.0,>=0.4.0)
Requires-Dist: numpy (<2.0,>=1.15.0)
Requires-Dist: deepmerge (<0.2.0,>=0.1.0)
Requires-Dist: pyshark (<0.5.0,>=0.4.2)
Requires-Dist: psutil (<6.0,>=5.6.0)
Requires-Dist: plotly (<5.0,>=4.11)
Requires-Dist: pandas (<2.0,>=1.1)
Requires-Dist: lxml (<5.0,>=4.5)
Requires-Dist: websockets (<9.0,>=8.0)
Provides-Extra: apps
Requires-Dist: motor (<3.0,>=2.3) ; extra == 'apps'
Requires-Dist: opencv-python (<4.6,>=4.5) ; extra == 'apps'
Requires-Dist: face-recognition (<1.4,>=1.3) ; extra == 'apps'
Provides-Extra: dev
Requires-Dist: autopep8 (<2.0,>=1.5) ; extra == 'dev'
Requires-Dist: pylint (<3.0,>=2.0) ; extra == 'dev'
Requires-Dist: rope (<1.0,>=0.16.0) ; extra == 'dev'
Requires-Dist: pytest (<6.0,>=5.0) ; extra == 'dev'
Requires-Dist: pytest-asyncio (<1.0,>=0.10.0) ; extra == 'dev'
Requires-Dist: docker (<5.0,>=4.0) ; extra == 'dev'
Requires-Dist: html5lib (<2.0,>=1.1) ; extra == 'dev'
Requires-Dist: bumpversion (<0.6.0,>=0.5.3) ; extra == 'dev'
